evalcards/__init__.py
evalcards/lang.py
evalcards/report.py
evalcards-0.2.11.dist-info/METADATA
evalcards-0.2.11.dist-info/WHEEL
evalcards-0.2.11.dist-info/entry_points.txt
evalcards-0.2.11.dist-info/licenses/LICENSE
evalcards-0.2.11.dist-info/RECORD
