Metadata-Version: 2.4
Name: evalcards
Version: 0.2.11
Summary: Reportes de evaluación (clasificación/regresión/forecast) a Markdown con gráficos
Project-URL: Homepage, https://github.com/Ricardouchub/evalcards
Project-URL: Repository, https://github.com/Ricardouchub/evalcards
Project-URL: Issues, https://github.com/Ricardouchub/evalcards/issues
Author-email: Ricardo Urdaneta <ricardourdanetacastro@gmail.com>
License: MIT
License-File: LICENSE
Classifier: License :: OSI Approved :: MIT License
Classifier: Operating System :: OS Independent
Classifier: Programming Language :: Python :: 3
Classifier: Programming Language :: Python :: 3 :: Only
Classifier: Programming Language :: Python :: 3.9
Classifier: Programming Language :: Python :: 3.10
Classifier: Programming Language :: Python :: 3.11
Classifier: Programming Language :: Python :: 3.12
Classifier: Programming Language :: Python :: 3.13
Requires-Python: >=3.9
Requires-Dist: jinja2>=3.1
Requires-Dist: matplotlib>=3.7
Requires-Dist: numpy>=1.22
Requires-Dist: pandas>=1.5
Requires-Dist: scikit-learn>=1.3
